{
	"ImportPath": "github.com/globocom/docker-cluster",
	"GoVersion": "devel +50235ae4e784 Wed Jan 22 13:30:12 2014 +0400",
	"Packages": [
		"./..."
	],
	"Deps": [
		{
			"ImportPath": "code.google.com/p/go.net/websocket",
			"Comment": "null-88",
			"Rev": "55437409069bb181ad562b1ad1e5f361c44aff17"
		},
		{
			"ImportPath": "code.google.com/p/gosqlite/sqlite3",
			"Comment": "null-16",
			"Rev": "74691fb6f83716190870cde1b658538dd4b18eb0"
		},
		{
			"ImportPath": "github.com/dotcloud/docker",
			"Comment": "v0.7.0",
			"Rev": "0d078b65817fc91eba916652b3f087a6c2eef851"
		},
		{
			"ImportPath": "github.com/dotcloud/tar",
			"Rev": "e5ea6bb21a3294bbbb8019a6cdcb1360f1c0a797"
		},
		{
			"ImportPath": "github.com/fsouza/go-dockerclient",
			"Rev": "270abd956f2f0e3216a02014ed502a1694e08478"
		},
		{
			"ImportPath": "github.com/garyburd/redigo/redis",
			"Rev": "8736767bf9f75f2374aac103059362a5c322d211"
		},
		{
			"ImportPath": "github.com/globocom/tsuru/safe",
			"Comment": "0.3.2-5-g9f42b32",
			"Rev": "9f42b32dddb19738b8077bf7aeccdae5a7f435d6"
		},
		{
			"ImportPath": "github.com/gorilla/context",
			"Rev": "708054d61e5a2918b9f4e9700000ee611dcf03f5"
		},
		{
			"ImportPath": "github.com/gorilla/mux",
			"Rev": "b08c5fcf14d01cb0c20ddf70157f54d4a2c3a38a"
		},
		{
			"ImportPath": "github.com/kr/pty",
			"Comment": "release.r56-14-g3b1f648",
			"Rev": "3b1f6487b7fc649d5f146df04e623bd55ba1bf7f"
		}
	]
}
